metoffice_weather_cli/__init__.py
metoffice_weather_cli/__main__.py
metoffice_weather_cli/configurator.py
metoffice_weather_cli/main.py
metoffice_weather_cli/weather.py
metoffice_weather_cli/weathercodes.py
metoffice_weather_cli-0.1.2.dist-info/LICENSE
metoffice_weather_cli-0.1.2.dist-info/METADATA
metoffice_weather_cli-0.1.2.dist-info/WHEEL
metoffice_weather_cli-0.1.2.dist-info/top_level.txt
metoffice_weather_cli-0.1.2.dist-info/RECORD
