Metadata-Version: 2.1
Name: metoffice-weather-cli
Version: 0.1.2
Summary: A CLI tool for fetching and printing weather data from the Met Office Weather DataHub API.
Author-email: corndogit <admin@corndogit.dev>
License: GNU GENERAL PUBLIC LICENSE
Project-URL: Homepage, https://github.com/corndogit/metoffice-weather-cli
Project-URL: Bug Tracker, https://github.com/corndogit/metoffice-weather-cli/issues
Classifier: Programming Language :: Python :: 3
Classifier: Operating System :: OS Independent
Requires-Python: >=3.10
License-File: LICENSE
Requires-Dist: python-dotenv >=1.0.0
Provides-Extra: dev
Requires-Dist: flake8 ~=6.0.0 ; extra == 'dev'
Provides-Extra: test
Requires-Dist: pytest ~=7.4.0 ; extra == 'test'
